README.md
setup.cfg
setup.py
examples/__init__.py
examples/context_example.py
examples/context_example_with_reset_func.py
examples/context_example_with_reset_func_2.py
examples/decorator_example.py
retry_helper/__init__.py
retry_helper/retry_manager.py
retry_helper.egg-info/PKG-INFO
retry_helper.egg-info/SOURCES.txt
retry_helper.egg-info/dependency_links.txt
retry_helper.egg-info/top_level.txt
tests/__init__.py