Metadata-Version: 2.1
Name: retry-helper
Version: 0.0.4
Summary: Helper for retrying code when exception occur
Home-page: https://github.com/lancondrej/retry-helper
Author: Ondřej Lanč
Author-email: ondrej.lanc@gmail.com
License: UNKNOWN
Platform: UNKNOWN
Classifier: Programming Language :: Python :: 3
Classifier: License :: OSI Approved :: Apache Software License
Classifier: Operating System :: OS Independent
Requires-Python: >=3.6
